abstractalgorithms/__init__.py
abstractalgorithms-0.1.dist-info/LICENSE
abstractalgorithms-0.1.dist-info/METADATA
abstractalgorithms-0.1.dist-info/WHEEL
abstractalgorithms-0.1.dist-info/top_level.txt
abstractalgorithms-0.1.dist-info/RECORD
