Metadata-Version: 2.1
Name: abstractalgorithms
Version: 0.1
Summary: Reference implementations of useful algos
Home-page: https://github.com/madgen-content/abstractalgorithms
Author: madgen
Author-email: madgencontent@gmail.com
License: UNKNOWN
Platform: UNKNOWN
